nnoir/__init__.py
nnoir/_version.py
nnoir/dot.py
nnoir/functions/__init__.py
nnoir/functions/add.py
nnoir/functions/add_constant.py
nnoir/functions/average_pooling_2d.py
nnoir/functions/batch_normalization.py
nnoir/functions/bias.py
nnoir/functions/bilinear_2d.py
nnoir/functions/broadcast.py
nnoir/functions/clipped_relu.py
nnoir/functions/concat.py
nnoir/functions/constant.py
nnoir/functions/convolution_2d.py
nnoir/functions/cos.py
nnoir/functions/depthwise_convolution_2d.py
nnoir/functions/div.py
nnoir/functions/dropout.py
nnoir/functions/elu.py
nnoir/functions/erf.py
nnoir/functions/exp.py
nnoir/functions/function.py
nnoir/functions/gemm.py
nnoir/functions/leaky_relu.py
nnoir/functions/linear.py
nnoir/functions/local_response_normalization.py
nnoir/functions/matmul.py
nnoir/functions/max_pooling_2d.py
nnoir/functions/mul.py
nnoir/functions/mul_constant.py
nnoir/functions/pad.py
nnoir/functions/relu.py
nnoir/functions/reshape.py
nnoir/functions/resize_2d.py
nnoir/functions/scale.py
nnoir/functions/sigmoid.py
nnoir/functions/sin.py
nnoir/functions/slice.py
nnoir/functions/softmax.py
nnoir/functions/softmax_cross_entropy.py
nnoir/functions/sqrt.py
nnoir/functions/sub.py
nnoir/functions/sum.py
nnoir/functions/swish.py
nnoir/functions/tan.py
nnoir/functions/tanh.py
nnoir/functions/transpose.py
nnoir/functions/unpooling_2d.py
nnoir/functions/util.py
nnoir/load.py
nnoir/metadata.py
nnoir/nnoir.py
nnoir/nntc.py
nnoir/py.typed
nnoir/runner.py
nnoir/value.py
nnoir-1.4.0.dist-info/METADATA
nnoir-1.4.0.dist-info/WHEEL
nnoir-1.4.0.dist-info/entry_points.txt
nnoir-1.4.0.dist-info/RECORD
