Metadata-Version: 2.3
Name: nnoir
Version: 1.4.0
Summary: API for NNOIR
License: MIT
Keywords: nnoir,machine learning
Author: Idein Inc.
Requires-Python: >=3.9,<4.0
Classifier: Development Status :: 4 - Beta
Classifier: Intended Audience :: Developers
Classifier: License :: OSI Approved :: MIT License
Classifier: Programming Language :: Python :: 3
Classifier: Programming Language :: Python :: 3.9
Classifier: Programming Language :: Python :: 3.10
Classifier: Programming Language :: Python :: 3.11
Classifier: Programming Language :: Python :: 3.12
Classifier: Programming Language :: Python :: 3.13
Classifier: Programming Language :: Python :: 3 :: Only
Requires-Dist: importlib-metadata (>=4,<5)
Requires-Dist: msgpack (>=1,<2)
Requires-Dist: numpy (>=1,<2)
Project-URL: Repository, https://github.com/Idein/nnoir/tree/master/nnoir
